emready/__init__.py
emready/bibtex.py
emready/constants.py
emready/protocols.conf
emready/protocols/__init__.py
emready/protocols/protocol_emready_sharpening.py
emready/tests/__init__.py
emready/tests/test_protocol_sharpening.py
scipion_em_emready-3.1.2.dist-info/LICENSE
scipion_em_emready-3.1.2.dist-info/METADATA
scipion_em_emready-3.1.2.dist-info/WHEEL
scipion_em_emready-3.1.2.dist-info/entry_points.txt
scipion_em_emready-3.1.2.dist-info/top_level.txt
scipion_em_emready-3.1.2.dist-info/RECORD
