Metadata-Version: 2.1
Name: scipion-em-emready
Version: 3.1.2
Summary: EMReady: Improvement of cryo-EM maps by simultaneous local and non-local deep learning
Author-email: Scipion Team <scipion@cnb.csic.es>, Jiahua He <d201880053@hust.edu.cn>, Tao Li <d202280084@hust.edu.cn>, Sheng-You Huang <huangsy@hust.edu.cn>
License: GNU General Public License v3 (GPLv3)
Project-URL: Homepage, https://github.com/scipion-em/scipion-em-emready
Project-URL: Issues, https://github.com/scipion-em/scipion-em-emready/issues
Keywords: scipion,cryoem,imageprocessing,scipion-3.0
Classifier: Development Status :: 4 - Beta
Classifier: License :: OSI Approved :: GNU General Public License v3 (GPLv3)
Classifier: Programming Language :: Python :: 3
Requires-Python: >=3.8
License-File: LICENSE
Requires-Dist: scipion-em
Requires-Dist: scipion-pyworkflow
